modupipe/__init__.py
modupipe/base.py
modupipe/exceptions.py
modupipe/extractor.py
modupipe/loader.py
modupipe/mapper.py
modupipe/queue.py
modupipe/runnable.py
modupipe-1.0.2.dist-info/LICENSE
modupipe-1.0.2.dist-info/WHEEL
modupipe-1.0.2.dist-info/METADATA
modupipe-1.0.2.dist-info/RECORD
