Metadata-Version: 2.1
Name: modupipe
Version: 1.0.2
Summary: A modular and extensible ETL-like pipeline builder
Home-page: https://github.com/vigenere23/modupipe
License: MIT
Keywords: pipeline,etl,pipe
Author: vigenere23
Author-email: lolgab1@hotmail.com
Requires-Python: >=3.9,<4.0
Classifier: License :: OSI Approved :: MIT License
Classifier: Programming Language :: Python :: 3
Classifier: Programming Language :: Python :: 3.10
Classifier: Programming Language :: Python :: 3.9
Project-URL: Repository, https://github.com/vigenere23/modupipe
